sns_notification_opsgenie/__init__.py
sns_notification_opsgenie/py.typed
sns_notification_opsgenie/_jsii/__init__.py
sns_notification_opsgenie/_jsii/sns-notification-opsgenie@1.1.0.jsii.tgz
sns_notification_opsgenie-1.1.0.dist-info/LICENSE
sns_notification_opsgenie-1.1.0.dist-info/METADATA
sns_notification_opsgenie-1.1.0.dist-info/WHEEL
sns_notification_opsgenie-1.1.0.dist-info/top_level.txt
sns_notification_opsgenie-1.1.0.dist-info/RECORD
